pyVat/__init__.py
pyVat/api.py
pyVat/validators/__init__.py
pyVat/validators/at.py
pyVat/validators/be.py
pyVat/validators/bg.py
pyVat/validators/cy.py
pyVat/validators/cz.py
pyVat/validators/de.py
pyVat/validators/dk.py
pyVat/validators/ee.py
pyVat/validators/es.py
pyVat/validators/fi.py
pyVat/validators/fr.py
pyVat/validators/gb.py
pyVat/validators/generic.py
pyVat/validators/gr.py
pyVat/validators/hr.py
pyVat/validators/hu.py
pyVat/validators/ie.py
pyVat/validators/it.py
pyVat/validators/lt.py
pyVat/validators/lu.py
pyVat/validators/lv.py
pyVat/validators/mt.py
pyVat/validators/nl.py
pyVat/validators/pl.py
pyVat/validators/pt.py
pyVat/validators/ro.py
pyVat/validators/se.py
pyVat/validators/si.py
pyVat/validators/sk.py
vat_format_checker-0.0.4.dist-info/AUTHORS
vat_format_checker-0.0.4.dist-info/LICENSE
vat_format_checker-0.0.4.dist-info/METADATA
vat_format_checker-0.0.4.dist-info/WHEEL
vat_format_checker-0.0.4.dist-info/top_level.txt
vat_format_checker-0.0.4.dist-info/RECORD
